{
	"cmake" : 
	{
		"generator" : 
		{
			"multiConfig" : false,
			"name" : "Unix Makefiles"
		},
		"paths" : 
		{
			"cmake" : "/usr/bin/cmake",
			"cpack" : "/usr/bin/cpack",
			"ctest" : "/usr/bin/ctest",
			"root" : "/usr/share/cmake-3.28"
		},
		"version" : 
		{
			"isDirty" : false,
			"major" : 3,
			"minor" : 28,
			"patch" : 3,
			"string" : "3.28.3",
			"suffix" : ""
		}
	},
	"objects" : 
	[
		{
<<<<<<<< HEAD:Facultate/Anul 1/Sem 2/OOP/Lab 6/cmake-build-debug/.cmake/api/v1/reply/index-2025-04-09T16-44-36-0972.json
			"jsonFile" : "codemodel-v2-362ea8c2ec1064733444.json",
========
			"jsonFile" : "codemodel-v2-eb730968cd1864541245.json",
>>>>>>>> f8a2f03abe2601334a4b2e837afee8c55c83aa43:Facultate/Anul 1/Sem 2/OOP/Lab 6/cmake-build-debug/.cmake/api/v1/reply/index-2025-04-10T05-01-46-0122.json
			"kind" : "codemodel",
			"version" : 
			{
				"major" : 2,
				"minor" : 6
			}
		},
		{
			"jsonFile" : "cache-v2-fa53f7b8a9452982fa8e.json",
			"kind" : "cache",
			"version" : 
			{
				"major" : 2,
				"minor" : 0
			}
		},
		{
<<<<<<<< HEAD:Facultate/Anul 1/Sem 2/OOP/Lab 6/cmake-build-debug/.cmake/api/v1/reply/index-2025-04-09T16-44-36-0972.json
			"jsonFile" : "cmakeFiles-v1-9b23b8fb6c8e79708b76.json",
========
			"jsonFile" : "cmakeFiles-v1-e2d64b937bcfebc94f18.json",
>>>>>>>> f8a2f03abe2601334a4b2e837afee8c55c83aa43:Facultate/Anul 1/Sem 2/OOP/Lab 6/cmake-build-debug/.cmake/api/v1/reply/index-2025-04-10T05-01-46-0122.json
			"kind" : "cmakeFiles",
			"version" : 
			{
				"major" : 1,
				"minor" : 0
			}
		},
		{
			"jsonFile" : "toolchains-v1-ee793ea44d57a62b2395.json",
			"kind" : "toolchains",
			"version" : 
			{
				"major" : 1,
				"minor" : 0
			}
		}
	],
	"reply" : 
	{
		"cache-v2" : 
		{
			"jsonFile" : "cache-v2-fa53f7b8a9452982fa8e.json",
			"kind" : "cache",
			"version" : 
			{
				"major" : 2,
				"minor" : 0
			}
		},
		"cmakeFiles-v1" : 
		{
<<<<<<<< HEAD:Facultate/Anul 1/Sem 2/OOP/Lab 6/cmake-build-debug/.cmake/api/v1/reply/index-2025-04-09T16-44-36-0972.json
			"jsonFile" : "cmakeFiles-v1-9b23b8fb6c8e79708b76.json",
========
			"jsonFile" : "cmakeFiles-v1-e2d64b937bcfebc94f18.json",
>>>>>>>> f8a2f03abe2601334a4b2e837afee8c55c83aa43:Facultate/Anul 1/Sem 2/OOP/Lab 6/cmake-build-debug/.cmake/api/v1/reply/index-2025-04-10T05-01-46-0122.json
			"kind" : "cmakeFiles",
			"version" : 
			{
				"major" : 1,
				"minor" : 0
			}
		},
		"codemodel-v2" : 
		{
<<<<<<<< HEAD:Facultate/Anul 1/Sem 2/OOP/Lab 6/cmake-build-debug/.cmake/api/v1/reply/index-2025-04-09T16-44-36-0972.json
			"jsonFile" : "codemodel-v2-362ea8c2ec1064733444.json",
========
			"jsonFile" : "codemodel-v2-eb730968cd1864541245.json",
>>>>>>>> f8a2f03abe2601334a4b2e837afee8c55c83aa43:Facultate/Anul 1/Sem 2/OOP/Lab 6/cmake-build-debug/.cmake/api/v1/reply/index-2025-04-10T05-01-46-0122.json
			"kind" : "codemodel",
			"version" : 
			{
				"major" : 2,
				"minor" : 6
			}
		},
		"toolchains-v1" : 
		{
			"jsonFile" : "toolchains-v1-ee793ea44d57a62b2395.json",
			"kind" : "toolchains",
			"version" : 
			{
				"major" : 1,
				"minor" : 0
			}
		}
	}
}
